libwdbo_bayesian.so
wdbo_criterion.cpython-39-i386-linux-gnu.so
wdbo_criterion-2.2.1.dist-info/top_level.txt
wdbo_criterion-2.2.1.dist-info/RECORD
wdbo_criterion-2.2.1.dist-info/METADATA
wdbo_criterion-2.2.1.dist-info/WHEEL
wdbo_criterion.libs/libgcc_s-8b50eaaa.so.1
wdbo_criterion.libs/libstdc++-8baf04f9.so.6.0.28
wdbo_criterion.libs/libwdbo_bayesian-34f32a31.so
